setup.py
pysmap/__init__.py
pysmap.egg-info/PKG-INFO
pysmap.egg-info/SOURCES.txt
pysmap.egg-info/dependency_links.txt
pysmap.egg-info/requires.txt
pysmap.egg-info/top_level.txt
pysmap/mltools/__init__.py
pysmap/mltools/crowd_model.py
pysmap/mltools/smapp_model.py
pysmap/twitterutil/__init__.py
pysmap/twitterutil/smapp_collection.py
pysmap/twitterutil/smapp_dataset.py
pysmap/viz/__init__.py
pysmap/viz/networks.py
pysmap/viz/plots.py
test/test_crowd_model.py
test/test_networks.py
test/test_plots.py
test/test_smapp_collection.py
test/test_smapp_dataset.py