Metadata-Version: 1.0
Name: pysmap
Version: 0.0.42
Summary: pysmap is a set of tools for working with twitter data
Home-page: https://github.com/SMAPPNYU/pysmap
Author: yvan
Author-email: yns207@nyu.edu
License: MIT
Keywords: twitter data tools pysmap
Platform: UNKNOWN
